Workbook

Sheet 仪表板
A1: 餐厅季度预算仪表板
A3: 全年预算收入 | C3: 全年实际收入 | E3: 全年预算利润 | G3: 全年实际利润 | I3: 实际利润率 | K3: 目标利润率
A4: =季度汇总!B9 | C4: =季度汇总!C9 | E4: =季度汇总!H9 | G4: =季度汇总!I9 | I4: =季度汇总!J9 | K4: =预算假设!B15
A7: 图表数据
A8: 季度 | B8: 预算收入 | C8: 实际收入 | D8: 预算利润 | E8: 实际利润 | F8: 实际利润率
A9: =季度汇总!A4 | B9: =季度汇总!B4 | C9: =季度汇总!C4 | D9: =季度汇总!H4 | E9: =季度汇总!I4 | F9: =季度汇总!J4
A10: =季度汇总!A5 | B10: =季度汇总!B5 | C10: =季度汇总!C5 | D10: =季度汇总!H5 | E10: =季度汇总!I5 | F10: =季度汇总!J5
A11: =季度汇总!A6 | B11: =季度汇总!B6 | C11: =季度汇总!C6 | D11: =季度汇总!H6 | E11: =季度汇总!I6 | F11: =季度汇总!J6
A12: =季度汇总!A7 | B12: =季度汇总!B7 | C12: =季度汇总!C7 | D12: =季度汇总!H7 | E12: =季度汇总!I7 | F12: =季度汇总!J7
A15: 全年成本费用结构
A16: 类别 | B16: 实际金额
A17: 食材成本 | B17: =SUMIFS(预算明细!$E:$E,预算明细!$C:$C,"食材成本")
A18: 人工成本 | B18: =SUMIFS(预算明细!$E:$E,预算明细!$C:$C,"人工成本")
A19: 租金物业 | B19: =SUMIFS(预算明细!$E:$E,预算明细!$C:$C,"租金物业")
A20: 水电燃气 | B20: =SUMIFS(预算明细!$E:$E,预算明细!$C:$C,"水电燃气")
A21: 市场推广 | B21: =SUMIFS(预算明细!$E:$E,预算明细!$C:$C,"市场推广")
A22: 其他费用 | B22: =SUMIFS(预算明细!$E:$E,预算明细!$C:$C,"维修杂项")+SUMIFS(预算明细!$E:$E,预算明细!$C:$C,"管理费用")

Sheet 预算假设
A1: 餐厅季度预算假设
A3: 项目 | B3: 金额/比例 | C3: 单位 | D3: 说明 | E3: 可调整 | F3: 备注
A4: 营业天数/季度 | B4: 91 | C4: 天 | D4: 用于按日计算收入与客流 | E4: 是 | F4: 按自然季度估算
A5: 客单价 | B5: 88 | C5: 元/人 | D5: 堂食与外卖综合客单价 | E5: 是
A6: 日均客流 | B6: 320 | C6: 人/天 | D6: 预算基准客流 | E6: 是
A7: 外卖收入占比 | B7: 0.24 | C7: % | D7: 外卖平台订单占总收入比例 | E7: 是
A8: 食材成本率 | B8: 0.32 | C8: % | D8: 食材采购占收入比例 | E8: 是
A9: 人工成本率 | B9: 0.22 | C9: % | D9: 薪资、社保与临时工 | E9: 是
A10: 租金/季度 | B10: 180000 | C10: 元 | D10: 固定租金与物业费 | E10: 是
A11: 水电燃气/季度 | B11: 76000 | C11: 元 | D11: 能源成本预算 | E11: 是
A12: 市场推广/季度 | B12: 56000 | C12: 元 | D12: 线上投放、会员活动 | E12: 是
A13: 维修与杂项/季度 | B13: 32000 | C13: 元 | D13: 设备维护与低值易耗 | E13: 是
A14: 管理费用/季度 | B14: 45000 | C14: 元 | D14: 办公、财务、行政支持 | E14: 是
A15: 目标利润率 | B15: 0.15 | C15: % | D15: 用于预算达标判断 | E15: 是

Sheet 预算明细
A1: 预算明细
A3: 季度 | B3: 类别 | C3: 项目 | D3: 预算金额 | E3: 实际金额 | F3: 差异 | G3: 差异率 | H3: 备注
A4: Q1 | B4: 收入 | C4: 堂食收入 | D4: =预算假设!$B$4*预算假设!$B$5*预算假设!$B$6*(1-预算假设!$B$7) | E4: 1830000 | F4: =E4-D4 | G4: =IF(D4=0,"",F4/D4)
A5: Q1 | B5: 收入 | C5: 外卖收入 | D5: =预算假设!$B$4*预算假设!$B$5*预算假设!$B$6*预算假设!$B$7 | E5: 590000 | F5: =E5-D5 | G5: =IF(D5=0,"",F5/D5)
A6: Q1 | B6: 成本 | C6: 食材成本 | D6: =SUMIFS($D:$D,$A:$A,A4,$B:$B,"收入")*预算假设!$B$8 | E6: 800000 | F6: =E6-D6 | G6: =IF(D6=0,"",F6/D6)
A7: Q1 | B7: 成本 | C7: 人工成本 | D7: =SUMIFS($D:$D,$A:$A,A4,$B:$B,"收入")*预算假设!$B$9 | E7: 545000 | F7: =E7-D7 | G7: =IF(D7=0,"",F7/D7)
A8: Q1 | B8: 成本 | C8: 租金物业 | D8: =预算假设!$B$10 | E8: 180000 | F8: =E8-D8 | G8: =IF(D8=0,"",F8/D8)
A9: Q1 | B9: 成本 | C9: 水电燃气 | D9: =预算假设!$B$11 | E9: 83000 | F9: =E9-D9 | G9: =IF(D9=0,"",F9/D9)
A10: Q1 | B10: 费用 | C10: 市场推广 | D10: =预算假设!$B$12 | E10: 65000 | F10: =E10-D10 | G10: =IF(D10=0,"",F10/D10)
A11: Q1 | B11: 费用 | C11: 维修杂项 | D11: =预算假设!$B$13 | E11: 36000 | F11: =E11-D11 | G11: =IF(D11=0,"",F11/D11)
A12: Q1 | B12: 费用 | C12: 管理费用 | D12: =预算假设!$B$14 | E12: 45000 | F12: =E12-D12 | G12: =IF(D12=0,"",F12/D12)
A13: Q2 | B13: 收入 | C13: 堂食收入 | D13: =D4*1.08 | E13: 1897344 | F13: =E13-D13 | G13: =IF(D13=0,"",F13/D13)
A14: Q2 | B14: 收入 | C14: 外卖收入 | D14: =D5*1.08 | E14: 611712 | F14: =E14-D14 | G14: =IF(D14=0,"",F14/D14)
A15: Q2 | B15: 成本 | C15: 食材成本 | D15: =D6*1.05 | E15: 806400 | F15: =E15-D15 | G15: =IF(D15=0,"",F15/D15)
A16: Q2 | B16: 成本 | C16: 人工成本 | D16: =D7*1.05 | E16: 549360 | F16: =E16-D16 | G16: =IF(D16=0,"",F16/D16)
A17: Q2 | B17: 成本 | C17: 租金物业 | D17: =D8*1.05 | E17: 181440 | F17: =E17-D17 | G17: =IF(D17=0,"",F17/D17)
A18: Q2 | B18: 成本 | C18: 水电燃气 | D18: =D9*1.05 | E18: 83664 | F18: =E18-D18 | G18: =IF(D18=0,"",F18/D18)
A19: Q2 | B19: 费用 | C19: 市场推广 | D19: =D10*0.98 | E19: 61152 | F19: =E19-D19 | G19: =IF(D19=0,"",F19/D19)
A20: Q2 | B20: 费用 | C20: 维修杂项 | D20: =D11*0.98 | E20: 33869 | F20: =E20-D20 | G20: =IF(D20=0,"",F20/D20)
A21: Q2 | B21: 费用 | C21: 管理费用 | D21: =D12*0.98 | E21: 42336 | F21: =E21-D21 | G21: =IF(D21=0,"",F21/D21)
A22: Q3 | B22: 收入 | C22: 堂食收入 | D22: =D4*1.15 | E22: 2146590 | F22: =E22-D22 | G22: =IF(D22=0,"",F22/D22)
A23: Q3 | B23: 收入 | C23: 外卖收入 | D23: =D5*1.15 | E23: 692070 | F23: =E23-D23 | G23: =IF(D23=0,"",F23/D23)
A24: Q3 | B24: 成本 | C24: 食材成本 | D24: =D6*1.1 | E24: 897600 | F24: =E24-D24 | G24: =IF(D24=0,"",F24/D24)
A25: Q3 | B25: 成本 | C25: 人工成本 | D25: =D7*1.1 | E25: 611490 | F25: =E25-D25 | G25: =IF(D25=0,"",F25/D25)
A26: Q3 | B26: 成本 | C26: 租金物业 | D26: =D8*1.1 | E26: 201960 | F26: =E26-D26 | G26: =IF(D26=0,"",F26/D26)
A27: Q3 | B27: 成本 | C27: 水电燃气 | D27: =D9*1.1 | E27: 93126 | F27: =E27-D27 | G27: =IF(D27=0,"",F27/D27)
A28: Q3 | B28: 费用 | C28: 市场推广 | D28: =D10*1.08 | E28: 71604 | F28: =E28-D28 | G28: =IF(D28=0,"",F28/D28)
A29: Q3 | B29: 费用 | C29: 维修杂项 | D29: =D11*1.08 | E29: 39658 | F29: =E29-D29 | G29: =IF(D29=0,"",F29/D29)
A30: Q3 | B30: 费用 | C30: 管理费用 | D30: =D12*1.08 | E30: 49572 | F30: =E30-D30 | G30: =IF(D30=0,"",F30/D30)
A31: Q4 | B31: 收入 | C31: 堂食收入 | D31: =D4*1.22 | E31: 2321904 | F31: =E31-D31 | G31: =IF(D31=0,"",F31/D31)
A32: Q4 | B32: 收入 | C32: 外卖收入 | D32: =D5*1.22 | E32: 748592 | F32: =E32-D32 | G32: =IF(D32=0,"",F32/D32)
A33: Q4 | B33: 成本 | C33: 食材成本 | D33: =D6*1.18 | E33: 981760 | F33: =E33-D33 | G33: =IF(D33=0,"",F33/D33)
A34: Q4 | B34: 成本 | C34: 人工成本 | D34: =D7*1.18 | E34: 668824 | F34: =E34-D34 | G34: =IF(D34=0,"",F34/D34)
A35: Q4 | B35: 成本 | C35: 租金物业 | D35: =D8*1.18 | E35: 220896 | F35: =E35-D35 | G35: =IF(D35=0,"",F35/D35)
A36: Q4 | B36: 成本 | C36: 水电燃气 | D36: =D9*1.18 | E36: 101858 | F36: =E36-D36 | G36: =IF(D36=0,"",F36/D36)
A37: Q4 | B37: 费用 | C37: 市场推广 | D37: =D10*1.12 | E37: 75712 | F37: =E37-D37 | G37: =IF(D37=0,"",F37/D37)
A38: Q4 | B38: 费用 | C38: 维修杂项 | D38: =D11*1.12 | E38: 41933 | F38: =E38-D38 | G38: =IF(D38=0,"",F38/D38)
A39: Q4 | B39: 费用 | C39: 管理费用 | D39: =D12*1.12 | E39: 52416 | F39: =E39-D39 | G39: =IF(D39=0,"",F39/D39)

Sheet 季度汇总
A1: 季度汇总与利润测算
A3: 季度 | B3: 预算收入 | C3: 实际收入 | D3: 预算成本 | E3: 实际成本 | F3: 预算费用 | G3: 实际费用 | H3: 预算利润 | I3: 实际利润 | J3: 实际利润率
A4: Q1 | B4: =SUMIFS(预算明细!$D:$D,预算明细!$A:$A,A4,预算明细!$B:$B,"收入") | C4: =SUMIFS(预算明细!$E:$E,预算明细!$A:$A,A4,预算明细!$B:$B,"收入") | D4: =SUMIFS(预算明细!$D:$D,预算明细!$A:$A,A4,预算明细!$B:$B,"成本") | E4: =SUMIFS(预算明细!$E:$E,预算明细!$A:$A,A4,预算明细!$B:$B,"成本") | F4: =SUMIFS(预算明细!$D:$D,预算明细!$A:$A,A4,预算明细!$B:$B,"费用") | G4: =SUMIFS(预算明细!$E:$E,预算明细!$A:$A,A4,预算明细!$B:$B,"费用") | H4: =B4-D4-F4 | I4: =C4-E4-G4 | J4: =IF(C4=0,"",I4/C4)
A5: Q2 | B5: =SUMIFS(预算明细!$D:$D,预算明细!$A:$A,A5,预算明细!$B:$B,"收入") | C5: =SUMIFS(预算明细!$E:$E,预算明细!$A:$A,A5,预算明细!$B:$B,"收入") | D5: =SUMIFS(预算明细!$D:$D,预算明细!$A:$A,A5,预算明细!$B:$B,"成本") | E5: =SUMIFS(预算明细!$E:$E,预算明细!$A:$A,A5,预算明细!$B:$B,"成本") | F5: =SUMIFS(预算明细!$D:$D,预算明细!$A:$A,A5,预算明细!$B:$B,"费用") | G5: =SUMIFS(预算明细!$E:$E,预算明细!$A:$A,A5,预算明细!$B:$B,"费用") | H5: =B5-D5-F5 | I5: =C5-E5-G5 | J5: =IF(C5=0,"",I5/C5)
A6: Q3 | B6: =SUMIFS(预算明细!$D:$D,预算明细!$A:$A,A6,预算明细!$B:$B,"收入") | C6: =SUMIFS(预算明细!$E:$E,预算明细!$A:$A,A6,预算明细!$B:$B,"收入") | D6: =SUMIFS(预算明细!$D:$D,预算明细!$A:$A,A6,预算明细!$B:$B,"成本") | E6: =SUMIFS(预算明细!$E:$E,预算明细!$A:$A,A6,预算明细!$B:$B,"成本") | F6: =SUMIFS(预算明细!$D:$D,预算明细!$A:$A,A6,预算明细!$B:$B,"费用") | G6: =SUMIFS(预算明细!$E:$E,预算明细!$A:$A,A6,预算明细!$B:$B,"费用") | H6: =B6-D6-F6 | I6: =C6-E6-G6 | J6: =IF(C6=0,"",I6/C6)
A7: Q4 | B7: =SUMIFS(预算明细!$D:$D,预算明细!$A:$A,A7,预算明细!$B:$B,"收入") | C7: =SUMIFS(预算明细!$E:$E,预算明细!$A:$A,A7,预算明细!$B:$B,"收入") | D7: =SUMIFS(预算明细!$D:$D,预算明细!$A:$A,A7,预算明细!$B:$B,"成本") | E7: =SUMIFS(预算明细!$E:$E,预算明细!$A:$A,A7,预算明细!$B:$B,"成本") | F7: =SUMIFS(预算明细!$D:$D,预算明细!$A:$A,A7,预算明细!$B:$B,"费用") | G7: =SUMIFS(预算明细!$E:$E,预算明细!$A:$A,A7,预算明细!$B:$B,"费用") | H7: =B7-D7-F7 | I7: =C7-E7-G7 | J7: =IF(C7=0,"",I7/C7)
A9: 全年合计 | B9: =SUM(B4:B7) | C9: =SUM(C4:C7) | D9: =SUM(D4:D7) | E9: =SUM(E4:E7) | F9: =SUM(F4:F7) | G9: =SUM(G4:G7) | H9: =SUM(H4:H7) | I9: =SUM(I4:I7) | J9: =IF(C9=0,"",I9/C9)

Sheet 检查
A1: 模型检查
A3: 检查项 | B3: 实际值 | C3: 期望值 | D3: 差异 | E3: 容忍度 | F3: 状态
A4: 收入汇总一致 | B4: =SUM(季度汇总!B4:B7) | C4: =SUMIFS(预算明细!D:D,预算明细!B:B,"收入") | D4: =B4-C4 | E4: 1 | F4: =IF(ABS(D4)<=E4,"OK","检查")
A5: 实际收入汇总一致 | B5: =SUM(季度汇总!C4:C7) | C5: =SUMIFS(预算明细!E:E,预算明细!B:B,"收入") | D5: =B5-C5 | E5: 1 | F5: =IF(ABS(D5)<=E5,"OK","检查")
A6: 利润率达标 | B6: =季度汇总!J9 | C6: =预算假设!B15 | D6: =B6-C6 | E6: 0 | F6: =IF(B6>=C6,"OK","关注")
